liveramp_automation/__init__.py
liveramp_automation/__version__.py
liveramp_automation/helpers/__init__.py
liveramp_automation/helpers/bigquery.py
liveramp_automation/helpers/bucket.py
liveramp_automation/helpers/file.py
liveramp_automation/helpers/fixture.py
liveramp_automation/helpers/grafana.py
liveramp_automation/helpers/login.py
liveramp_automation/helpers/notification.py
liveramp_automation/helpers/sftp_client.py
liveramp_automation/plugins/__init__.py
liveramp_automation/plugins/bbm_reporter.py
liveramp_automation/plugins/test_rail_report_plugin.py
liveramp_automation/utils/__init__.py
liveramp_automation/utils/allure.py
liveramp_automation/utils/log.py
liveramp_automation/utils/pagerduty.py
liveramp_automation/utils/parsers.py
liveramp_automation/utils/playwright.py
liveramp_automation/utils/report.py
liveramp_automation/utils/request.py
liveramp_automation/utils/selenium.py
liveramp_automation/utils/slack.py
liveramp_automation/utils/steps.py
liveramp_automation/utils/testrail.py
liveramp_automation/utils/time.py
liveramp_automation-1.8.4.dist-info/LICENSE
liveramp_automation-1.8.4.dist-info/METADATA
liveramp_automation-1.8.4.dist-info/WHEEL
liveramp_automation-1.8.4.dist-info/entry_points.txt
liveramp_automation-1.8.4.dist-info/top_level.txt
liveramp_automation-1.8.4.dist-info/RECORD
