Metadata-Version: 2.1
Name: liveramp-automation
Version: 1.8.4
Summary: This is the base liveramp_automation_framework
Home-page: https://github.com/LiveRamp/liveramp-automation
Author: Jasmine Qian
Author-email: jasmine.qian@liveramp.com
License-File: LICENSE
Requires-Dist: allure-pytest-bdd
Requires-Dist: allure-python-commons
Requires-Dist: boto3
Requires-Dist: certifi
Requires-Dist: datadog
Requires-Dist: db-dtypes
Requires-Dist: dnspython
Requires-Dist: google
Requires-Dist: google-api-core
Requires-Dist: google-auth
Requires-Dist: google-cloud-bigquery
Requires-Dist: google-cloud-core
Requires-Dist: google-cloud-storage
Requires-Dist: google-crc32c
Requires-Dist: google-resumable-media
Requires-Dist: googleapis-common-protos
Requires-Dist: httpx
Requires-Dist: mysql-connector-python
Requires-Dist: pandas
Requires-Dist: paramiko
Requires-Dist: playwright
Requires-Dist: pytest
Requires-Dist: pytest-bdd
Requires-Dist: pytest-json
Requires-Dist: pytest-json-report
Requires-Dist: pytest-xdist
Requires-Dist: pytest-rerunfailures
Requires-Dist: python-dotenv
Requires-Dist: PyYAML
Requires-Dist: requests
Requires-Dist: retrying
Requires-Dist: selenium==4.16.0
Requires-Dist: singlestoredb
Requires-Dist: snowflake-connector-python
